pygls/__init__.py
pygls/capabilities.py
pygls/client.py
pygls/constants.py
pygls/exceptions.py
pygls/feature_manager.py
pygls/lsp/__init__.py
pygls/lsp/client.py
pygls/progress.py
pygls/protocol/__init__.py
pygls/protocol/json_rpc.py
pygls/protocol/language_server.py
pygls/protocol/lsp_meta.py
pygls/py.typed
pygls/server.py
pygls/uris.py
pygls/workspace/__init__.py
pygls/workspace/position_codec.py
pygls/workspace/text_document.py
pygls/workspace/workspace.py
pygls-1.2.0.dist-info/LICENSE.txt
pygls-1.2.0.dist-info/METADATA
pygls-1.2.0.dist-info/WHEEL
pygls-1.2.0.dist-info/RECORD
