Metadata-Version: 2.1
Name: pygls
Version: 1.2.0
Summary: A pythonic generic language server (pronounced like 'pie glass')
Home-page: https://github.com/openlawlibrary/pygls
License: Apache 2.0
Author: Open Law Library
Author-email: info@openlawlib.org
Maintainer: Tom BH
Maintainer-email: tom@tombh.co.uk
Requires-Python: >=3.7.9,<4
Classifier: License :: Other/Proprietary License
Classifier: Programming Language :: Python :: 3
Classifier: Programming Language :: Python :: 3.8
Classifier: Programming Language :: Python :: 3.9
Classifier: Programming Language :: Python :: 3.10
Classifier: Programming Language :: Python :: 3.11
Classifier: Programming Language :: Python :: 3.12
Provides-Extra: ws
Requires-Dist: lsprotocol (==2023.0.0)
Requires-Dist: websockets (>=11.0.3,<12.0.0) ; extra == "ws"
Project-URL: Documentation, https://pygls.readthedocs.io/en/latest
Project-URL: Repository, https://github.com/openlawlibrary/pygls
